setup.py
ksuid/__init__.py
ksuid/ksuid.py
ksuid/ksuid_test.py
ksuid/utils.py
ksuid.egg-info/PKG-INFO
ksuid.egg-info/SOURCES.txt
ksuid.egg-info/dependency_links.txt
ksuid.egg-info/not-zip-safe
ksuid.egg-info/pbr.json
ksuid.egg-info/top_level.txt