Metadata-Version: 1.0
Name: ksuid
Version: 1.2
Summary: A small python package for creating ksuids
Home-page: https://github.com/Samuel-Resendez/KSUID
Author: Samuel Resendez
Author-email: samresendez1@gmail.com
License: MIT
Platform: UNKNOWN
